meval_fork/__init__.py
EblomevalZeticsce-1.3.dist-info/LICENSE
EblomevalZeticsce-1.3.dist-info/METADATA
EblomevalZeticsce-1.3.dist-info/WHEEL
EblomevalZeticsce-1.3.dist-info/top_level.txt
EblomevalZeticsce-1.3.dist-info/RECORD
